LICENSE
MANIFEST.in
README.md
requirements.txt
setup.py
pycontractsdk/__init__.py
pycontractsdk/abi.py
pycontractsdk/config.py
pycontractsdk/contracts.py
pycontractsdk/events.py
pycontractsdk/exception.py
pycontractsdk/keys.py
pycontractsdk/test.py
pycontractsdk/utils.py
pycontractsdk.v2.egg-info/PKG-INFO
pycontractsdk.v2.egg-info/SOURCES.txt
pycontractsdk.v2.egg-info/dependency_links.txt
pycontractsdk.v2.egg-info/entry_points.txt
pycontractsdk.v2.egg-info/not-zip-safe
pycontractsdk.v2.egg-info/requires.txt
pycontractsdk.v2.egg-info/top_level.txt
pycontractsdk/mycontracts/__init__.py
pycontractsdk/mycontracts/cport.py
pycontractsdk/mycontracts/proof.py
pycontractsdk/mycontracts/starcoin.py
pycontractsdk/mycontracts/starcoinv2.py